pyty/__init__.py
pyty/exception.py
pyty_lang-0.0.6.dist-info/METADATA
pyty_lang-0.0.6.dist-info/WHEEL
pyty_lang-0.0.6.dist-info/entry_points.txt
pyty_lang-0.0.6.dist-info/licenses/LICENSE
pyty_lang-0.0.6.dist-info/RECORD
